filemaker/__init__.py
filemaker/__main__.py
filemaker/filemaker_api.py
filemaker_api-1.0.1.dist-info/LICENSE
filemaker_api-1.0.1.dist-info/METADATA
filemaker_api-1.0.1.dist-info/WHEEL
filemaker_api-1.0.1.dist-info/entry_points.txt
filemaker_api-1.0.1.dist-info/top_level.txt
filemaker_api-1.0.1.dist-info/RECORD
