Metadata-Version: 2.1
Name: filemaker-api
Version: 1.0.1
Summary: Connect easily to a FileMaker instance.
Home-page: https://caoslab.psy.cmu.edu:32443/caoskids/filemaker_api
Author: Hugo Angulo
Author-email: hugoanda@andrew.cmu.edu
License: MIT
Platform: UNKNOWN
Classifier: License :: OSI Approved :: MIT License
Classifier: Programming Language :: Python :: 3
Classifier: Programming Language :: Python :: 3.7
Requires-Dist: requests
